adpac_auth1/__init__.py
adpac_auth1/module.py
adpac_auth1-0.0.2.dist-info/METADATA
adpac_auth1-0.0.2.dist-info/WHEEL
adpac_auth1-0.0.2.dist-info/top_level.txt
adpac_auth1-0.0.2.dist-info/RECORD
